{
  "areaName": "namanga",
  "aliases": [
    "nammanga"
  ],
  "geojson": {
    "type": "FeatureCollection",
    "features": [
      {
        "type": "Feature",
        "properties": {},
        "geometry": {
          "coordinates": [
            [
              [
                36.807325565020506,
                -2.5500296784072134
              ],
              [
                36.83381481153964,
                -2.538397528240779
              ],
              [
                36.81183746827307,
                -2.527783101812929
              ],
              [
                36.78112740582776,
                -2.5362164888188943
              ],
              [
                36.807325565020506,
                -2.5500296784072134
              ]
            ]
          ],
          "type": "Polygon"
        }
      }
    ]
  }
}